README.md
setup.cfg
setup.py
lp_accounts/__init__.py
lp_accounts/admin.py
lp_accounts/apps.py
lp_accounts/factories.py
lp_accounts/models.py
lp_accounts/serializers.py
lp_accounts/signals.py
lp_accounts/urls.py
lp_accounts/views.py
lp_accounts.egg-info/PKG-INFO
lp_accounts.egg-info/SOURCES.txt
lp_accounts.egg-info/dependency_links.txt
lp_accounts.egg-info/requires.txt
lp_accounts.egg-info/top_level.txt
lp_accounts/migrations/0001_initial.py
lp_accounts/migrations/0002_user_is_confirmed.py
lp_accounts/migrations/0003_auto_20171031_0151.py
lp_accounts/migrations/0004_auto_20171031_1627.py
lp_accounts/migrations/0005_remove_user_type.py
lp_accounts/migrations/__init__.py
lp_accounts/validators/linkedin.py