Metadata-Version: 1.2
Name: lp-accounts
Version: 2.1.3
Summary: REST Framework for User Accounts
Home-page: https://github.com/Launchpeer/django-rest-account
Author: Jim Simon
Author-email: hello@launchpeer.com
License: UNKNOWN
Download-URL: https://github.com/Launchpeer/django-rest-account/archive/master.tar.gz
Platform: UNKNOWN
Requires-Python: >=3
